{
    "properties": [
        {
            "modifiers": [], 
            "name": "taskIndexOrder", 
            "visibility": "PUBLIC", 
            "references": [], 
            "location": {
                "column": 37, 
                "line": 37
            }, 
            "type": "Double"
        }, 
        {
            "modifiers": [], 
            "name": "actionPlanTemplate", 
            "visibility": "PUBLIC", 
            "references": [], 
            "location": {
                "column": 37, 
                "line": 38
            }, 
            "type": "ActionPlanTemplate__c"
        }, 
        {
            "modifiers": [], 
            "name": "aptTasks", 
            "visibility": "PUBLIC", 
            "references": [], 
            "location": {
                "column": 37, 
                "line": 39
            }, 
            "type": "LIST"
        }, 
        {
            "modifiers": [], 
            "name": "actionPlan", 
            "visibility": "PUBLIC", 
            "references": [], 
            "location": {
                "column": 37, 
                "line": 40
            }, 
            "type": "ActionPlan__c"
        }, 
        {
            "modifiers": [], 
            "name": "apTasks", 
            "visibility": "PUBLIC", 
            "references": [], 
            "location": {
                "column": 37, 
                "line": 41
            }, 
            "type": "LIST"
        }, 
        {
            "modifiers": [], 
            "name": "apTasksOrg", 
            "visibility": "PUBLIC", 
            "references": [], 
            "location": {
                "column": 37, 
                "line": 42
            }, 
            "type": "LIST"
        }, 
        {
            "modifiers": [], 
            "name": "errorMsg", 
            "visibility": "PUBLIC", 
            "references": [], 
            "location": {
                "column": 37, 
                "line": 43
            }, 
            "type": "String"
        }, 
        {
            "modifiers": [], 
            "name": "pendingTemplateDeletes", 
            "visibility": "PUBLIC", 
            "references": [], 
            "location": {
                "column": 37, 
                "line": 44
            }, 
            "type": "LIST"
        }, 
        {
            "modifiers": [], 
            "name": "pendingDeletes", 
            "visibility": "PUBLIC", 
            "references": [], 
            "location": {
                "column": 37, 
                "line": 45
            }, 
            "type": "LIST"
        }, 
        {
            "modifiers": [], 
            "name": "taskLimit", 
            "visibility": "PUBLIC", 
            "references": [], 
            "location": {
                "column": 37, 
                "line": 46
            }, 
            "type": "Integer"
        }, 
        {
            "modifiers": [], 
            "name": "relatedObjIds", 
            "visibility": "PUBLIC", 
            "references": [], 
            "location": {
                "column": 37, 
                "line": 47
            }, 
            "type": "LIST"
        }, 
        {
            "modifiers": [], 
            "name": "relatedObjName", 
            "visibility": "PUBLIC", 
            "references": [], 
            "location": {
                "column": 37, 
                "line": 48
            }, 
            "type": "String"
        }, 
        {
            "modifiers": [], 
            "name": "relatedObjOwnerList", 
            "visibility": "PUBLIC", 
            "references": [], 
            "location": {
                "column": 37, 
                "line": 49
            }, 
            "type": "Map"
        }
    ], 
    "methods": [
        {
            "modifiers": [], 
            "name": "getRelatedObjName", 
            "parameters": [], 
            "visibility": "PUBLIC", 
            "references": [], 
            "location": {
                "column": 19, 
                "line": 80
            }, 
            "returnType": "String", 
            "type": null
        }, 
        {
            "modifiers": [], 
            "name": "relatedObjIds", 
            "parameters": [], 
            "visibility": "PUBLIC", 
            "references": [], 
            "location": {
                "column": 25, 
                "line": 88
            }, 
            "returnType": "LIST", 
            "type": null
        }, 
        {
            "modifiers": [], 
            "name": "getActionPlans", 
            "parameters": [], 
            "visibility": "PUBLIC", 
            "references": [], 
            "location": {
                "column": 32, 
                "line": 96
            }, 
            "returnType": "LIST", 
            "type": null
        }, 
        {
            "modifiers": [], 
            "name": "checkCycleDependent", 
            "parameters": [], 
            "visibility": "PUBLIC", 
            "references": [], 
            "location": {
                "column": 20, 
                "line": 130
            }, 
            "returnType": "Boolean", 
            "type": null
        }, 
        {
            "modifiers": [], 
            "name": "dependentCycleWorker", 
            "parameters": [], 
            "visibility": "PUBLIC", 
            "references": [], 
            "location": {
                "column": 20, 
                "line": 178
            }, 
            "returnType": "Boolean", 
            "type": null
        }, 
        {
            "modifiers": [], 
            "name": "dependantCycle", 
            "parameters": [
                {
                    "type": "APTaskTemplate__c", 
                    "name": "originTask"
                }, 
                {
                    "type": "APTaskTemplate__c", 
                    "name": "destinyTask"
                }, 
                {
                    "type": "Integer", 
                    "name": "index"
                }
            ], 
            "visibility": "PRIVATE", 
            "references": [], 
            "location": {
                "column": 21, 
                "line": 230
            }, 
            "returnType": "Boolean", 
            "type": null
        }, 
        {
            "modifiers": [], 
            "name": "saveAp", 
            "parameters": [], 
            "visibility": "PUBLIC", 
            "references": [], 
            "location": {
                "column": 19, 
                "line": 276
            }, 
            "returnType": "String", 
            "type": null
        }, 
        {
            "modifiers": [], 
            "name": "checkPendingDeletes", 
            "parameters": [], 
            "visibility": "PUBLIC", 
            "references": [], 
            "location": {
                "column": 17, 
                "line": 331
            }, 
            "returnType": "void", 
            "type": null
        }, 
        {
            "modifiers": [], 
            "name": "setDependencies", 
            "parameters": [
                {
                    "type": "LIST", 
                    "name": "input"
                }
            ], 
            "visibility": "PUBLIC", 
            "references": [], 
            "location": {
                "column": 17, 
                "line": 348
            }, 
            "returnType": "void", 
            "type": null
        }, 
        {
            "modifiers": [], 
            "name": "save", 
            "parameters": [], 
            "visibility": "PUBLIC", 
            "references": [], 
            "location": {
                "column": 26, 
                "line": 377
            }, 
            "returnType": "PageReference", 
            "type": null
        }, 
        {
            "modifiers": [], 
            "name": "saveHandler", 
            "parameters": [], 
            "visibility": "PUBLIC", 
            "references": [], 
            "location": {
                "column": 26, 
                "line": 401
            }, 
            "returnType": "PageReference", 
            "type": null
        }, 
        {
            "modifiers": [], 
            "name": "saveMultiple", 
            "parameters": [], 
            "visibility": "PUBLIC", 
            "references": [], 
            "location": {
                "column": 26, 
                "line": 420
            }, 
            "returnType": "PageReference", 
            "type": null
        }, 
        {
            "modifiers": [], 
            "name": "saveAndNew", 
            "parameters": [], 
            "visibility": "PUBLIC", 
            "references": [], 
            "location": {
                "column": 26, 
                "line": 576
            }, 
            "returnType": "PageReference", 
            "type": null
        }, 
        {
            "modifiers": [], 
            "name": "cancel", 
            "parameters": [], 
            "visibility": "PUBLIC", 
            "references": [], 
            "location": {
                "column": 26, 
                "line": 588
            }, 
            "returnType": "PageReference", 
            "type": null
        }, 
        {
            "modifiers": [], 
            "name": "getTasks", 
            "parameters": [], 
            "visibility": "PUBLIC", 
            "references": [], 
            "location": {
                "column": 36, 
                "line": 636
            }, 
            "returnType": "LIST", 
            "type": null
        }, 
        {
            "modifiers": [], 
            "name": "addTask", 
            "parameters": [], 
            "visibility": "PUBLIC", 
            "references": [], 
            "location": {
                "column": 20, 
                "line": 727
            }, 
            "returnType": "Boolean", 
            "type": null
        }, 
        {
            "modifiers": [], 
            "name": "removeTask", 
            "parameters": [], 
            "visibility": "PUBLIC", 
            "references": [], 
            "location": {
                "column": 20, 
                "line": 757
            }, 
            "returnType": "Boolean", 
            "type": null
        }, 
        {
            "modifiers": [], 
            "name": "getTaskSize", 
            "parameters": [], 
            "visibility": "PUBLIC", 
            "references": [], 
            "location": {
                "column": 20, 
                "line": 809
            }, 
            "returnType": "Integer", 
            "type": null
        }, 
        {
            "modifiers": [], 
            "name": "getSubjectItems", 
            "parameters": [], 
            "visibility": "PUBLIC", 
            "references": [], 
            "location": {
                "column": 31, 
                "line": 817
            }, 
            "returnType": "LIST", 
            "type": null
        }, 
        {
            "modifiers": [], 
            "name": "getSelectedItems", 
            "parameters": [], 
            "visibility": "PUBLIC", 
            "references": [], 
            "location": {
                "column": 31, 
                "line": 835
            }, 
            "returnType": "LIST", 
            "type": null
        }, 
        {
            "modifiers": [], 
            "name": "getSelectedSubjectItems", 
            "parameters": [], 
            "visibility": "PUBLIC", 
            "references": [], 
            "location": {
                "column": 37, 
                "line": 853
            }, 
            "returnType": "LIST", 
            "type": null
        }, 
        {
            "modifiers": [], 
            "name": "getCompleted", 
            "parameters": [], 
            "visibility": "PUBLIC", 
            "references": [], 
            "location": {
                "column": 20, 
                "line": 887
            }, 
            "returnType": "Integer", 
            "type": null
        }, 
        {
            "modifiers": [], 
            "name": "deletePlan", 
            "parameters": [], 
            "visibility": "PUBLIC", 
            "references": [], 
            "location": {
                "column": 26, 
                "line": 903
            }, 
            "returnType": "PageReference", 
            "type": null
        }, 
        {
            "modifiers": [], 
            "name": "getVersion", 
            "parameters": [], 
            "visibility": "PUBLIC", 
            "references": [], 
            "location": {
                "column": 20, 
                "line": 931
            }, 
            "returnType": "Boolean", 
            "type": null
        }, 
        {
            "modifiers": [], 
            "name": "getCustomSetting", 
            "parameters": [], 
            "visibility": "PUBLIC", 
            "references": [], 
            "location": {
                "column": 37, 
                "line": 945
            }, 
            "returnType": "Action_Plans_Settings__c", 
            "type": null
        }, 
        {
            "modifiers": [], 
            "name": "getObjectKeyPrefix", 
            "parameters": [
                {
                    "type": "String", 
                    "name": "objName"
                }
            ], 
            "visibility": "PUBLIC", 
            "references": [], 
            "location": {
                "column": 19, 
                "line": 958
            }, 
            "returnType": "String", 
            "type": null
        }, 
        {
            "modifiers": [], 
            "name": "getPostObjectBody", 
            "parameters": [
                {
                    "type": "String", 
                    "name": "objName"
                }
            ], 
            "visibility": "PUBLIC", 
            "references": [], 
            "location": {
                "column": 19, 
                "line": 968
            }, 
            "returnType": "String", 
            "type": null
        }, 
        {
            "modifiers": [], 
            "name": "generateObjectFeed", 
            "parameters": [
                {
                    "type": "String", 
                    "name": "apId"
                }
            ], 
            "visibility": "PUBLIC", 
            "references": [], 
            "location": {
                "column": 17, 
                "line": 978
            }, 
            "returnType": "void", 
            "type": null
        }, 
        {
            "modifiers": [], 
            "name": "getRecordOwnerId", 
            "parameters": [
                {
                    "type": "ActionPlan__c", 
                    "name": "ap"
                }
            ], 
            "visibility": "PUBLIC", 
            "references": [], 
            "location": {
                "column": 19, 
                "line": 1049
            }, 
            "returnType": "String", 
            "type": null
        }, 
        {
            "modifiers": [], 
            "name": "isObjectEnabledFeed", 
            "parameters": [
                {
                    "type": "ActionPlan__c", 
                    "name": "ap"
                }
            ], 
            "visibility": "PUBLIC", 
            "references": [], 
            "location": {
                "column": 20, 
                "line": 1073
            }, 
            "returnType": "Boolean", 
            "type": null
        }, 
        {
            "modifiers": [], 
            "name": "isFeedEnabled", 
            "parameters": [
                {
                    "type": "String", 
                    "name": "objName"
                }
            ], 
            "visibility": "PUBLIC", 
            "references": [], 
            "location": {
                "column": 20, 
                "line": 1090
            }, 
            "returnType": "Boolean", 
            "type": null
        }, 
        {
            "modifiers": [], 
            "name": "getHoursOption", 
            "parameters": [], 
            "visibility": "PUBLIC", 
            "references": [], 
            "location": {
                "column": 31, 
                "line": 1124
            }, 
            "returnType": "LIST", 
            "type": null
        }, 
        {
            "modifiers": [], 
            "name": "retrieveTaskFromExistingActionPlan", 
            "parameters": [
                {
                    "type": "String", 
                    "name": "actionPlanId"
                }
            ], 
            "visibility": "PUBLIC", 
            "references": [], 
            "location": {
                "column": 36, 
                "line": 1184
            }, 
            "returnType": "LIST", 
            "type": null
        }, 
        {
            "modifiers": [], 
            "name": "hasRelatedObject", 
            "parameters": [], 
            "visibility": "PUBLIC", 
            "references": [], 
            "location": {
                "column": 20, 
                "line": 1200
            }, 
            "returnType": "Boolean", 
            "type": null
        }, 
        {
            "modifiers": [], 
            "name": "getRelatedObjectOptions", 
            "parameters": [], 
            "visibility": "PUBLIC", 
            "references": [], 
            "location": {
                "column": 31, 
                "line": 1212
            }, 
            "returnType": "LIST", 
            "type": null
        }, 
        {
            "modifiers": [], 
            "name": "getDefaultRelatedObjectOption", 
            "parameters": [], 
            "visibility": "PUBLIC", 
            "references": [], 
            "location": {
                "column": 25, 
                "line": 1230
            }, 
            "returnType": "SelectOption", 
            "type": null
        }, 
        {
            "modifiers": [], 
            "name": "relatedObjectId", 
            "parameters": [], 
            "visibility": "PUBLIC", 
            "references": [], 
            "location": {
                "column": 15, 
                "line": 1238
            }, 
            "returnType": "Id", 
            "type": null
        }, 
        {
            "modifiers": [], 
            "name": "truncateId", 
            "parameters": [
                {
                    "type": "Object", 
                    "name": "longId"
                }
            ], 
            "visibility": "PUBLIC", 
            "references": [], 
            "location": {
                "column": 19, 
                "line": 1255
            }, 
            "returnType": "String", 
            "type": null
        }, 
        {
            "modifiers": [], 
            "name": "retrieveOwnersDataRelatedObject", 
            "parameters": [
                {
                    "type": "LIST", 
                    "name": "relatedObjIds"
                }, 
                {
                    "type": "String", 
                    "name": "relatedObjectName"
                }
            ], 
            "visibility": "PUBLIC", 
            "references": [], 
            "location": {
                "column": 17, 
                "line": 1265
            }, 
            "returnType": "void", 
            "type": null
        }, 
        {
            "modifiers": [], 
            "name": "concat", 
            "parameters": [
                {
                    "type": "LIST", 
                    "name": "stringList"
                }, 
                {
                    "type": "String", 
                    "name": "separator"
                }
            ], 
            "visibility": "PRIVATE", 
            "references": [], 
            "location": {
                "column": 20, 
                "line": 1287
            }, 
            "returnType": "String", 
            "type": null
        }, 
        {
            "modifiers": [], 
            "name": "validateChangeStatus", 
            "parameters": [
                {
                    "type": "String", 
                    "name": "apTaskId"
                }
            ], 
            "visibility": "PUBLIC", 
            "references": [], 
            "location": {
                "column": 20, 
                "line": 1305
            }, 
            "returnType": "Boolean", 
            "type": null
        }, 
        {
            "modifiers": [], 
            "name": "getDisplayReminder", 
            "parameters": [], 
            "visibility": "PUBLIC", 
            "references": [], 
            "location": {
                "column": 20, 
                "line": 1381
            }, 
            "returnType": "Boolean", 
            "type": null
        }, 
        {
            "modifiers": [], 
            "name": "getReminderDefaultTime", 
            "parameters": [], 
            "visibility": "PUBLIC", 
            "references": [], 
            "location": {
                "column": 19, 
                "line": 1390
            }, 
            "returnType": "String", 
            "type": null
        }, 
        {
            "modifiers": [], 
            "name": "deleteActionPlans", 
            "parameters": [], 
            "visibility": "PUBLIC", 
            "references": [], 
            "location": {
                "column": 26, 
                "line": 1409
            }, 
            "returnType": "PageReference", 
            "type": null
        }, 
        {
            "modifiers": [], 
            "name": "retrieveAPNameFromTemplate", 
            "parameters": [
                {
                    "type": "ActionPlanTemplate__c", 
                    "name": "actionPlanTemplate"
                }
            ], 
            "visibility": "PUBLIC", 
            "references": [], 
            "location": {
                "column": 19, 
                "line": 1434
            }, 
            "returnType": "String", 
            "type": null
        }, 
        {
            "modifiers": [
                "STATIC"
            ], 
            "name": "parseMultiSelect", 
            "parameters": [
                {
                    "type": "String", 
                    "name": "input"
                }
            ], 
            "visibility": "PUBLIC", 
            "references": [], 
            "location": {
                "column": 32, 
                "line": 104
            }, 
            "returnType": "LIST", 
            "type": null
        }
    ], 
    "innerClasses": [
        {
            "properties": [], 
            "methods": [], 
            "innerClasses": [], 
            "variables": [], 
            "constructors": [], 
            "namespace": null, 
            "name": "MyException", 
            "tableDeclaration": {
                "type": "MyException", 
                "modifiers": [], 
                "references": [], 
                "location": {
                    "column": 18, 
                    "line": 51
                }, 
                "name": "MyException"
            }, 
            "key": null, 
            "id": null, 
            "externalReferences": []
        }
    ], 
    "variables": [
        {
            "type": "StandardController", 
            "modifiers": [], 
            "references": [], 
            "location": {
                "column": 63, 
                "line": 61
            }, 
            "name": "stdController"
        }, 
        {
            "type": "ActionPlan__c", 
            "modifiers": [], 
            "references": [], 
            "location": {
                "column": 48, 
                "line": 67
            }, 
            "name": "action"
        }, 
        {
            "type": "Integer", 
            "modifiers": [], 
            "references": [], 
            "location": {
                "column": 17, 
                "line": 133
            }, 
            "name": "index"
        }, 
        {
            "type": "Integer", 
            "modifiers": [], 
            "references": [], 
            "location": {
                "column": 21, 
                "line": 135
            }, 
            "name": "k"
        }, 
        {
            "type": "APTaskTemplate__c", 
            "modifiers": [], 
            "references": [], 
            "location": {
                "column": 32, 
                "line": 140
            }, 
            "name": "t"
        }, 
        {
            "type": "LIST", 
            "modifiers": [], 
            "references": [], 
            "location": {
                "column": 30, 
                "line": 144
            }, 
            "name": "selectedValues"
        }, 
        {
            "type": "String", 
            "modifiers": [], 
            "references": [], 
            "location": {
                "column": 29, 
                "line": 146
            }, 
            "name": "i"
        }, 
        {
            "type": "Integer", 
            "modifiers": [], 
            "references": [], 
            "location": {
                "column": 29, 
                "line": 147
            }, 
            "name": "tempIndex"
        }, 
        {
            "type": "APTaskTemplate__c", 
            "modifiers": [], 
            "references": [], 
            "location": {
                "column": 39, 
                "line": 148
            }, 
            "name": "link"
        }, 
        {
            "type": "Integer", 
            "modifiers": [], 
            "references": [], 
            "location": {
                "column": 21, 
                "line": 166
            }, 
            "name": "k"
        }, 
        {
            "type": "Map", 
            "modifiers": [], 
            "references": [], 
            "location": {
                "column": 35, 
                "line": 180
            }, 
            "name": "children"
        }, 
        {
            "type": "Integer", 
            "modifiers": [], 
            "references": [], 
            "location": {
                "column": 17, 
                "line": 181
            }, 
            "name": "l"
        }, 
        {
            "type": "Set", 
            "modifiers": [], 
            "references": [], 
            "location": {
                "column": 26, 
                "line": 184
            }, 
            "name": "parent"
        }, 
        {
            "type": "LIST", 
            "modifiers": [], 
            "references": [], 
            "location": {
                "column": 30, 
                "line": 186
            }, 
            "name": "selectedValues"
        }, 
        {
            "type": "String", 
            "modifiers": [], 
            "references": [], 
            "location": {
                "column": 29, 
                "line": 187
            }, 
            "name": "p"
        }, 
        {
            "type": "Integer", 
            "modifiers": [], 
            "references": [], 
            "location": {
                "column": 29, 
                "line": 188
            }, 
            "name": "tempIndex"
        }, 
        {
            "type": "Set", 
            "modifiers": [], 
            "references": [], 
            "location": {
                "column": 26, 
                "line": 201
            }, 
            "name": "looker"
        }, 
        {
            "type": "LIST", 
            "modifiers": [], 
            "references": [], 
            "location": {
                "column": 27, 
                "line": 202
            }, 
            "name": "holder"
        }, 
        {
            "type": "Integer", 
            "modifiers": [], 
            "references": [], 
            "location": {
                "column": 21, 
                "line": 207
            }, 
            "name": "x"
        }, 
        {
            "type": "Integer", 
            "modifiers": [], 
            "references": [], 
            "location": {
                "column": 29, 
                "line": 211
            }, 
            "name": "j"
        }, 
        {
            "type": "APTaskTemplate__c", 
            "modifiers": [], 
            "references": [], 
            "location": {
                "column": 55, 
                "line": 230
            }, 
            "name": "originTask"
        }, 
        {
            "type": "APTaskTemplate__c", 
            "modifiers": [], 
            "references": [], 
            "location": {
                "column": 85, 
                "line": 230
            }, 
            "name": "destinyTask"
        }, 
        {
            "type": "Integer", 
            "modifiers": [], 
            "references": [], 
            "location": {
                "column": 106, 
                "line": 230
            }, 
            "name": "index"
        }, 
        {
            "type": "Boolean", 
            "modifiers": [], 
            "references": [], 
            "location": {
                "column": 17, 
                "line": 232
            }, 
            "name": "hasDependency"
        }, 
        {
            "type": "Set", 
            "modifiers": [], 
            "references": [], 
            "location": {
                "column": 22, 
                "line": 233
            }, 
            "name": "visitedTasks"
        }, 
        {
            "type": "LIST", 
            "modifiers": [], 
            "references": [], 
            "location": {
                "column": 22, 
                "line": 234
            }, 
            "name": "selectedDestinyValues"
        }, 
        {
            "type": "Integer", 
            "modifiers": [], 
            "references": [], 
            "location": {
                "column": 25, 
                "line": 248
            }, 
            "name": "tempIndexDestiny"
        }, 
        {
            "type": "APTaskTemplate__c", 
            "modifiers": [], 
            "references": [], 
            "location": {
                "column": 35, 
                "line": 249
            }, 
            "name": "link"
        }, 
        {
            "type": "Integer", 
            "modifiers": [], 
            "references": [], 
            "location": {
                "column": 33, 
                "line": 258
            }, 
            "name": "tempIndex"
        }, 
        {
            "type": "String", 
            "modifiers": [], 
            "references": [], 
            "location": {
                "column": 16, 
                "line": 279
            }, 
            "name": "actionPlanId"
        }, 
        {
            "type": "String", 
            "modifiers": [], 
            "references": [], 
            "location": {
                "column": 16, 
                "line": 280
            }, 
            "name": "objId"
        }, 
        {
            "type": "String", 
            "modifiers": [], 
            "references": [], 
            "location": {
                "column": 16, 
                "line": 281
            }, 
            "name": "objName"
        }, 
        {
            "type": "LIST", 
            "modifiers": [], 
            "references": [], 
            "location": {
                "column": 22, 
                "line": 282
            }, 
            "name": "oIdsList"
        }, 
        {
            "type": "Savepoint", 
            "modifiers": [], 
            "references": [], 
            "location": {
                "column": 19, 
                "line": 283
            }, 
            "name": "sp"
        }, 
        {
            "type": "ActionPlansBatchBuilder", 
            "modifiers": [], 
            "references": [], 
            "location": {
                "column": 41, 
                "line": 313
            }, 
            "name": "taskBatch"
        }, 
        {
            "type": "ActionPlansBatchBuilderUtilities", 
            "modifiers": [], 
            "references": [], 
            "location": {
                "column": 50, 
                "line": 316
            }, 
            "name": "taskBatch"
        }, 
        {
            "type": "LIST", 
            "modifiers": [], 
            "references": [], 
            "location": {
                "column": 25, 
                "line": 334
            }, 
            "name": "taskToDelete"
        }, 
        {
            "type": "LIST", 
            "modifiers": [], 
            "references": [], 
            "location": {
                "column": 25, 
                "line": 335
            }, 
            "name": "deleteApttIds"
        }, 
        {
            "type": "APTaskTemplate__c", 
            "modifiers": [], 
            "references": [], 
            "location": {
                "column": 36, 
                "line": 337
            }, 
            "name": "deleteAptt"
        }, 
        {
            "type": "LIST", 
            "modifiers": [], 
            "references": [], 
            "location": {
                "column": 54, 
                "line": 348
            }, 
            "name": "input"
        }, 
        {
            "type": "Integer", 
            "modifiers": [], 
            "references": [], 
            "location": {
                "column": 25, 
                "line": 356
            }, 
            "name": "i"
        }, 
        {
            "type": "String", 
            "modifiers": [], 
            "references": [], 
            "location": {
                "column": 24, 
                "line": 357
            }, 
            "name": "val"
        }, 
        {
            "type": "Integer", 
            "modifiers": [], 
            "references": [], 
            "location": {
                "column": 33, 
                "line": 360
            }, 
            "name": "j"
        }, 
        {
            "type": "String", 
            "modifiers": [], 
            "references": [], 
            "location": {
                "column": 16, 
                "line": 379
            }, 
            "name": "newApId"
        }, 
        {
            "type": "String", 
            "modifiers": [], 
            "references": [], 
            "location": {
                "column": 16, 
                "line": 390
            }, 
            "name": "ap_list"
        }, 
        {
            "type": "PageReference", 
            "modifiers": [], 
            "references": [], 
            "location": {
                "column": 23, 
                "line": 391
            }, 
            "name": "newPage"
        }, 
        {
            "type": "String", 
            "modifiers": [], 
            "references": [], 
            "location": {
                "column": 16, 
                "line": 403
            }, 
            "name": "oIds"
        }, 
        {
            "type": "LIST", 
            "modifiers": [], 
            "references": [], 
            "location": {
                "column": 22, 
                "line": 404
            }, 
            "name": "oIdsList"
        }, 
        {
            "type": "String", 
            "modifiers": [], 
            "references": [], 
            "location": {
                "column": 16, 
                "line": 422
            }, 
            "name": "oName"
        }, 
        {
            "type": "String", 
            "modifiers": [], 
            "references": [], 
            "location": {
                "column": 16, 
                "line": 423
            }, 
            "name": "oIds"
        }, 
        {
            "type": "LIST", 
            "modifiers": [], 
            "references": [], 
            "location": {
                "column": 29, 
                "line": 424
            }, 
            "name": "apList"
        }, 
        {
            "type": "LIST", 
            "modifiers": [], 
            "references": [], 
            "location": {
                "column": 33, 
                "line": 425
            }, 
            "name": "aptList"
        }, 
        {
            "type": "Savepoint", 
            "modifiers": [], 
            "references": [], 
            "location": {
                "column": 19, 
                "line": 426
            }, 
            "name": "sp"
        }, 
        {
            "type": "LIST", 
            "modifiers": [], 
            "references": [], 
            "location": {
                "column": 30, 
                "line": 432
            }, 
            "name": "oIdsList"
        }, 
        {
            "type": "ActionPlansBatchBuilder", 
            "modifiers": [], 
            "references": [], 
            "location": {
                "column": 41, 
                "line": 439
            }, 
            "name": "taskBatch"
        }, 
        {
            "type": "PageReference", 
            "modifiers": [], 
            "references": [], 
            "location": {
                "column": 23, 
                "line": 451
            }, 
            "name": "newPage"
        }, 
        {
            "type": "PageReference", 
            "modifiers": [], 
            "references": [], 
            "location": {
                "column": 23, 
                "line": 578
            }, 
            "name": "newPage"
        }, 
        {
            "type": "String", 
            "modifiers": [], 
            "references": [], 
            "location": {
                "column": 16, 
                "line": 589
            }, 
            "name": "objectType"
        }, 
        {
            "type": "String", 
            "modifiers": [], 
            "references": [], 
            "location": {
                "column": 16, 
                "line": 590
            }, 
            "name": "objectIds"
        }, 
        {
            "type": "String", 
            "modifiers": [], 
            "references": [], 
            "location": {
                "column": 16, 
                "line": 591
            }, 
            "name": "templateId"
        }, 
        {
            "type": "String", 
            "modifiers": [], 
            "references": [], 
            "location": {
                "column": 16, 
                "line": 592
            }, 
            "name": "retURL"
        }, 
        {
            "type": "String", 
            "modifiers": [], 
            "references": [], 
            "location": {
                "column": 16, 
                "line": 593
            }, 
            "name": "id"
        }, 
        {
            "type": "String", 
            "modifiers": [], 
            "references": [], 
            "location": {
                "column": 16, 
                "line": 594
            }, 
            "name": "pageRef"
        }, 
        {
            "type": "String", 
            "modifiers": [], 
            "references": [], 
            "location": {
                "column": 16, 
                "line": 595
            }, 
            "name": "aPlanListUrl"
        }, 
        {
            "type": "LIST", 
            "modifiers": [], 
            "references": [], 
            "location": {
                "column": 26, 
                "line": 606
            }, 
            "name": "oIdsList"
        }, 
        {
            "type": "PageReference", 
            "modifiers": [], 
            "references": [], 
            "location": {
                "column": 23, 
                "line": 626
            }, 
            "name": "previousPage"
        }, 
        {
            "type": "String", 
            "modifiers": [], 
            "references": [], 
            "location": {
                "column": 24, 
                "line": 640
            }, 
            "name": "tempApId"
        }, 
        {
            "type": "Action_Plans_Settings__c", 
            "modifiers": [], 
            "references": [], 
            "location": {
                "column": 42, 
                "line": 650
            }, 
            "name": "mySettings"
        }, 
        {
            "type": "String", 
            "modifiers": [], 
            "references": [], 
            "location": {
                "column": 24, 
                "line": 651
            }, 
            "name": "userId"
        }, 
        {
            "type": "APTTaskTemplate__c", 
            "modifiers": [], 
            "references": [], 
            "location": {
                "column": 41, 
                "line": 652
            }, 
            "name": "aptTask"
        }, 
        {
            "type": "APTaskTemplate__c", 
            "modifiers": [], 
            "references": [], 
            "location": {
                "column": 39, 
                "line": 667
            }, 
            "name": "t"
        }, 
        {
            "type": "String", 
            "modifiers": [], 
            "references": [], 
            "location": {
                "column": 24, 
                "line": 683
            }, 
            "name": "TempApId"
        }, 
        {
            "type": "String", 
            "modifiers": [], 
            "references": [], 
            "location": {
                "column": 24, 
                "line": 686
            }, 
            "name": "tmp_remainderDefaultTime"
        }, 
        {
            "type": "APTaskTemplate__c", 
            "modifiers": [], 
            "references": [], 
            "location": {
                "column": 40, 
                "line": 687
            }, 
            "name": "t"
        }, 
        {
            "type": "APTaskTemplate__c", 
            "modifiers": [], 
            "references": [], 
            "location": {
                "column": 35, 
                "line": 696
            }, 
            "name": "t"
        }, 
        {
            "type": "LIST", 
            "modifiers": [], 
            "references": [], 
            "location": {
                "column": 41, 
                "line": 704
            }, 
            "name": "tC"
        }, 
        {
            "type": "APTaskTemplate__c", 
            "modifiers": [], 
            "references": [], 
            "location": {
                "column": 40, 
                "line": 709
            }, 
            "name": "t"
        }, 
        {
            "type": "Boolean", 
            "modifiers": [], 
            "references": [], 
            "location": {
                "column": 17, 
                "line": 729
            }, 
            "name": "hasNoErrors"
        }, 
        {
            "type": "APTaskTemplate__c", 
            "modifiers": [], 
            "references": [], 
            "location": {
                "column": 31, 
                "line": 734
            }, 
            "name": "t"
        }, 
        {
            "type": "Action_Plans_Settings__c", 
            "modifiers": [], 
            "references": [], 
            "location": {
                "column": 38, 
                "line": 741
            }, 
            "name": "mySettings"
        }, 
        {
            "type": "APTaskTemplate__c", 
            "modifiers": [], 
            "references": [], 
            "location": {
                "column": 36, 
                "line": 742
            }, 
            "name": "apt"
        }, 
        {
            "type": "Boolean", 
            "modifiers": [], 
            "references": [], 
            "location": {
                "column": 17, 
                "line": 759
            }, 
            "name": "removedTask"
        }, 
        {
            "type": "Integer", 
            "modifiers": [], 
            "references": [], 
            "location": {
                "column": 21, 
                "line": 761
            }, 
            "name": "taskIndex"
        }, 
        {
            "type": "APTaskTemplate__c", 
            "modifiers": [], 
            "references": [], 
            "location": {
                "column": 31, 
                "line": 767
            }, 
            "name": "apTask"
        }, 
        {
            "type": "Integer", 
            "modifiers": [], 
            "references": [], 
            "location": {
                "column": 21, 
                "line": 768
            }, 
            "name": "dependentApTask"
        }, 
        {
            "type": "Integer", 
            "modifiers": [], 
            "references": [], 
            "location": {
                "column": 26, 
                "line": 771
            }, 
            "name": "i"
        }, 
        {
            "type": "LIST", 
            "modifiers": [], 
            "references": [], 
            "location": {
                "column": 28, 
                "line": 819
            }, 
            "name": "options"
        }, 
        {
            "type": "Integer", 
            "modifiers": [], 
            "references": [], 
            "location": {
                "column": 17, 
                "line": 821
            }, 
            "name": "i"
        }, 
        {
            "type": "APTaskTemplate__c", 
            "modifiers": [], 
            "references": [], 
            "location": {
                "column": 36, 
                "line": 824
            }, 
            "name": "t"
        }, 
        {
            "type": "LIST", 
            "modifiers": [], 
            "references": [], 
            "location": {
                "column": 28, 
                "line": 836
            }, 
            "name": "options"
        }, 
        {
            "type": "Integer", 
            "modifiers": [], 
            "references": [], 
            "location": {
                "column": 17, 
                "line": 838
            }, 
            "name": "i"
        }, 
        {
            "type": "APTaskTemplate__c", 
            "modifiers": [], 
            "references": [], 
            "location": {
                "column": 36, 
                "line": 841
            }, 
            "name": "t"
        }, 
        {
            "type": "LIST", 
            "modifiers": [], 
            "references": [], 
            "location": {
                "column": 34, 
                "line": 855
            }, 
            "name": "options"
        }, 
        {
            "type": "Integer", 
            "modifiers": [], 
            "references": [], 
            "location": {
                "column": 17, 
                "line": 857
            }, 
            "name": "i"
        }, 
        {
            "type": "Map", 
            "modifiers": [], 
            "references": [], 
            "location": {
                "column": 29, 
                "line": 858
            }, 
            "name": "taskMap"
        }, 
        {
            "type": "APTaskTemplate__c", 
            "modifiers": [], 
            "references": [], 
            "location": {
                "column": 32, 
                "line": 859
            }, 
            "name": "t"
        }, 
        {
            "type": "APTaskTemplate__c", 
            "modifiers": [], 
            "references": [], 
            "location": {
                "column": 36, 
                "line": 864
            }, 
            "name": "t"
        }, 
        {
            "type": "LIST", 
            "modifiers": [], 
            "references": [], 
            "location": {
                "column": 34, 
                "line": 868
            }, 
            "name": "tmp"
        }, 
        {
            "type": "String", 
            "modifiers": [], 
            "references": [], 
            "location": {
                "column": 32, 
                "line": 869
            }, 
            "name": "s"
        }, 
        {
            "type": "LIST", 
            "modifiers": [], 
            "references": [], 
            "location": {
                "column": 33, 
                "line": 889
            }, 
            "name": "ts"
        }, 
        {
            "type": "String", 
            "modifiers": [], 
            "references": [], 
            "location": {
                "column": 16, 
                "line": 890
            }, 
            "name": "tempApId"
        }, 
        {
            "type": "Savepoint", 
            "modifiers": [], 
            "references": [], 
            "location": {
                "column": 19, 
                "line": 905
            }, 
            "name": "sp"
        }, 
        {
            "type": "LIST", 
            "modifiers": [], 
            "references": [], 
            "location": {
                "column": 22, 
                "line": 907
            }, 
            "name": "recordIds"
        }, 
        {
            "type": "ActionPlansBatchDeleteUtilities", 
            "modifiers": [], 
            "references": [], 
            "location": {
                "column": 45, 
                "line": 912
            }, 
            "name": "taskBatch"
        }, 
        {
            "type": "String", 
            "modifiers": [], 
            "references": [], 
            "location": {
                "column": 16, 
                "line": 920
            }, 
            "name": "aPlanListUrl"
        }, 
        {
            "type": "PageReference", 
            "modifiers": [], 
            "references": [], 
            "location": {
                "column": 23, 
                "line": 921
            }, 
            "name": "newPage"
        }, 
        {
            "type": "ActionPlanTemplate__c", 
            "modifiers": [], 
            "references": [], 
            "location": {
                "column": 35, 
                "line": 933
            }, 
            "name": "TempApt"
        }, 
        {
            "type": "Action_Plans_Settings__c", 
            "modifiers": [], 
            "references": [], 
            "location": {
                "column": 34, 
                "line": 946
            }, 
            "name": "instance"
        }, 
        {
            "type": "String", 
            "modifiers": [], 
            "references": [], 
            "location": {
                "column": 46, 
                "line": 958
            }, 
            "name": "objName"
        }, 
        {
            "type": "DescribeSObjectResult", 
            "modifiers": [], 
            "references": [], 
            "location": {
                "column": 38, 
                "line": 959
            }, 
            "name": "obj"
        }, 
        {
            "type": "String", 
            "modifiers": [], 
            "references": [], 
            "location": {
                "column": 45, 
                "line": 968
            }, 
            "name": "objName"
        }, 
        {
            "type": "DescribeSObjectResult", 
            "modifiers": [], 
            "references": [], 
            "location": {
                "column": 38, 
                "line": 969
            }, 
            "name": "obj"
        }, 
        {
            "type": "String", 
            "modifiers": [], 
            "references": [], 
            "location": {
                "column": 44, 
                "line": 978
            }, 
            "name": "apId"
        }, 
        {
            "type": "String", 
            "modifiers": [], 
            "references": [], 
            "location": {
                "column": 16, 
                "line": 980
            }, 
            "name": "objId"
        }, 
        {
            "type": "String", 
            "modifiers": [], 
            "references": [], 
            "location": {
                "column": 16, 
                "line": 981
            }, 
            "name": "objName"
        }, 
        {
            "type": "Boolean", 
            "modifiers": [], 
            "references": [], 
            "location": {
                "column": 17, 
                "line": 982
            }, 
            "name": "chatter_enabled"
        }, 
        {
            "type": "DescribeSObjectResult", 
            "modifiers": [], 
            "references": [], 
            "location": {
                "column": 38, 
                "line": 983
            }, 
            "name": "r"
        }, 
        {
            "type": "ActionPlan__c", 
            "modifiers": [], 
            "references": [], 
            "location": {
                "column": 23, 
                "line": 985
            }, 
            "name": "ap"
        }, 
        {
            "type": "SObjectType", 
            "modifiers": [], 
            "references": [], 
            "location": {
                "column": 26, 
                "line": 1033
            }, 
            "name": "token"
        }, 
        {
            "type": "SObject", 
            "modifiers": [], 
            "references": [], 
            "location": {
                "column": 22, 
                "line": 1034
            }, 
            "name": "objPost"
        }, 
        {
            "type": "ActionPlan__c", 
            "modifiers": [], 
            "references": [], 
            "location": {
                "column": 51, 
                "line": 1049
            }, 
            "name": "ap"
        }, 
        {
            "type": "String", 
            "modifiers": [], 
            "references": [], 
            "location": {
                "column": 16, 
                "line": 1051
            }, 
            "name": "recoveredValue"
        }, 
        {
            "type": "String", 
            "modifiers": [], 
            "references": [], 
            "location": {
                "column": 16, 
                "line": 1052
            }, 
            "name": "objId"
        }, 
        {
            "type": "ActionPlan__c", 
            "modifiers": [], 
            "references": [], 
            "location": {
                "column": 55, 
                "line": 1073
            }, 
            "name": "ap"
        }, 
        {
            "type": "String", 
            "modifiers": [], 
            "references": [], 
            "location": {
                "column": 16, 
                "line": 1075
            }, 
            "name": "objName"
        }, 
        {
            "type": "String", 
            "modifiers": [], 
            "references": [], 
            "location": {
                "column": 42, 
                "line": 1090
            }, 
            "name": "objName"
        }, 
        {
            "type": "DescribeSObjectResult", 
            "modifiers": [], 
            "references": [], 
            "location": {
                "column": 38, 
                "line": 1091
            }, 
            "name": "obj"
        }, 
        {
            "type": "LIST", 
            "modifiers": [], 
            "references": [], 
            "location": {
                "column": 28, 
                "line": 1126
            }, 
            "name": "options"
        }, 
        {
            "type": "String", 
            "modifiers": [], 
            "references": [], 
            "location": {
                "column": 79, 
                "line": 1184
            }, 
            "name": "actionPlanId"
        }, 
        {
            "type": "LIST", 
            "modifiers": [], 
            "references": [], 
            "location": {
                "column": 33, 
                "line": 1186
            }, 
            "name": "myList"
        }, 
        {
            "type": "Boolean", 
            "modifiers": [], 
            "references": [], 
            "location": {
                "column": 17, 
                "line": 1201
            }, 
            "name": "hasRelated"
        }, 
        {
            "type": "LIST", 
            "modifiers": [], 
            "references": [], 
            "location": {
                "column": 32, 
                "line": 1214
            }, 
            "name": "options"
        }, 
        {
            "type": "Id", 
            "modifiers": [], 
            "references": [], 
            "location": {
                "column": 12, 
                "line": 1239
            }, 
            "name": "currentId"
        }, 
        {
            "type": "Object", 
            "modifiers": [], 
            "references": [], 
            "location": {
                "column": 37, 
                "line": 1255
            }, 
            "name": "longId"
        }, 
        {
            "type": "String", 
            "modifiers": [], 
            "references": [], 
            "location": {
                "column": 16, 
                "line": 1256
            }, 
            "name": "longIdString"
        }, 
        {
            "type": "LIST", 
            "modifiers": [], 
            "references": [], 
            "location": {
                "column": 63, 
                "line": 1265
            }, 
            "name": "relatedObjIds"
        }, 
        {
            "type": "String", 
            "modifiers": [], 
            "references": [], 
            "location": {
                "column": 85, 
                "line": 1265
            }, 
            "name": "relatedObjectName"
        }, 
        {
            "type": "String", 
            "modifiers": [], 
            "references": [], 
            "location": {
                "column": 16, 
                "line": 1267
            }, 
            "name": "shortId"
        }, 
        {
            "type": "String", 
            "modifiers": [], 
            "references": [], 
            "location": {
                "column": 16, 
                "line": 1268
            }, 
            "name": "queryRetrieveOwnerIds"
        }, 
        {
            "type": "SObject", 
            "modifiers": [], 
            "references": [], 
            "location": {
                "column": 26, 
                "line": 1274
            }, 
            "name": "obj"
        }, 
        {
            "type": "LIST", 
            "modifiers": [], 
            "references": [], 
            "location": {
                "column": 41, 
                "line": 1287
            }, 
            "name": "stringList"
        }, 
        {
            "type": "String", 
            "modifiers": [], 
            "references": [], 
            "location": {
                "column": 60, 
                "line": 1287
            }, 
            "name": "separator"
        }, 
        {
            "type": "String", 
            "modifiers": [], 
            "references": [], 
            "location": {
                "column": 16, 
                "line": 1289
            }, 
            "name": "result"
        }, 
        {
            "type": "String", 
            "modifiers": [], 
            "references": [], 
            "location": {
                "column": 21, 
                "line": 1290
            }, 
            "name": "elem"
        }, 
        {
            "type": "String", 
            "modifiers": [], 
            "references": [], 
            "location": {
                "column": 48, 
                "line": 1305
            }, 
            "name": "apTaskId"
        }, 
        {
            "type": "Boolean", 
            "modifiers": [], 
            "references": [], 
            "location": {
                "column": 17, 
                "line": 1306
            }, 
            "name": "result"
        }, 
        {
            "type": "Set", 
            "modifiers": [], 
            "references": [], 
            "location": {
                "column": 21, 
                "line": 1307
            }, 
            "name": "rejectStatus"
        }, 
        {
            "type": "LIST", 
            "modifiers": [], 
            "references": [], 
            "location": {
                "column": 33, 
                "line": 1308
            }, 
            "name": "currentAP"
        }, 
        {
            "type": "Set", 
            "modifiers": [], 
            "references": [], 
            "location": {
                "column": 33, 
                "line": 1309
            }, 
            "name": "nonComplete"
        }, 
        {
            "type": "LIST", 
            "modifiers": [], 
            "references": [], 
            "location": {
                "column": 33, 
                "line": 1311
            }, 
            "name": "aptList"
        }, 
        {
            "type": "String", 
            "modifiers": [], 
            "references": [], 
            "location": {
                "column": 16, 
                "line": 1315
            }, 
            "name": "actionPlan"
        }, 
        {
            "type": "LIST", 
            "modifiers": [], 
            "references": [], 
            "location": {
                "column": 22, 
                "line": 1316
            }, 
            "name": "dependencies"
        }, 
        {
            "type": "LIST", 
            "modifiers": [], 
            "references": [], 
            "location": {
                "column": 23, 
                "line": 1317
            }, 
            "name": "dependenciesI"
        }, 
        {
            "type": "Integer", 
            "modifiers": [], 
            "references": [], 
            "location": {
                "column": 21, 
                "line": 1319
            }, 
            "name": "i"
        }, 
        {
            "type": "String", 
            "modifiers": [], 
            "references": [], 
            "location": {
                "column": 20, 
                "line": 1327
            }, 
            "name": "d"
        }, 
        {
            "type": "Integer", 
            "modifiers": [], 
            "references": [], 
            "location": {
                "column": 21, 
                "line": 1331
            }, 
            "name": "i"
        }, 
        {
            "type": "Integer", 
            "modifiers": [], 
            "references": [], 
            "location": {
                "column": 21, 
                "line": 1338
            }, 
            "name": "i"
        }, 
        {
            "type": "Map", 
            "modifiers": [], 
            "references": [], 
            "location": {
                "column": 42, 
                "line": 1382
            }, 
            "name": "fieldsMap"
        }, 
        {
            "type": "Map", 
            "modifiers": [], 
            "references": [], 
            "location": {
                "column": 42, 
                "line": 1391
            }, 
            "name": "fieldsMap"
        }, 
        {
            "type": "String", 
            "modifiers": [], 
            "references": [], 
            "location": {
                "column": 16, 
                "line": 1392
            }, 
            "name": "defaultTime"
        }, 
        {
            "type": "LIST", 
            "modifiers": [], 
            "references": [], 
            "location": {
                "column": 30, 
                "line": 1394
            }, 
            "name": "uP"
        }, 
        {
            "type": "String", 
            "modifiers": [], 
            "references": [], 
            "location": {
                "column": 16, 
                "line": 1410
            }, 
            "name": "retURL"
        }, 
        {
            "type": "LIST", 
            "modifiers": [], 
            "references": [], 
            "location": {
                "column": 22, 
                "line": 1411
            }, 
            "name": "recordIds"
        }, 
        {
            "type": "String", 
            "modifiers": [], 
            "references": [], 
            "location": {
                "column": 20, 
                "line": 1416
            }, 
            "name": "records"
        }, 
        {
            "type": "ActionPlansBatchDelete", 
            "modifiers": [], 
            "references": [], 
            "location": {
                "column": 40, 
                "line": 1419
            }, 
            "name": "aPBatch"
        }, 
        {
            "type": "PageReference", 
            "modifiers": [], 
            "references": [], 
            "location": {
                "column": 23, 
                "line": 1424
            }, 
            "name": "pageRef"
        }, 
        {
            "type": "ActionPlanTemplate__c", 
            "modifiers": [], 
            "references": [], 
            "location": {
                "column": 68, 
                "line": 1434
            }, 
            "name": "actionPlanTemplate"
        }, 
        {
            "type": "String", 
            "modifiers": [], 
            "references": [], 
            "location": {
                "column": 16, 
                "line": 1436
            }, 
            "name": "aPName"
        }, 
        {
            "type": "String", 
            "modifiers": [], 
            "references": [], 
            "location": {
                "column": 56, 
                "line": 104
            }, 
            "name": "input"
        }, 
        {
            "type": "LIST", 
            "modifiers": [], 
            "references": [], 
            "location": {
                "column": 22, 
                "line": 107
            }, 
            "name": "values"
        }, 
        {
            "type": "String", 
            "modifiers": [], 
            "references": [], 
            "location": {
                "column": 16, 
                "line": 108
            }, 
            "name": "cleaned"
        }, 
        {
            "type": "Integer", 
            "modifiers": [], 
            "references": [], 
            "location": {
                "column": 21, 
                "line": 117
            }, 
            "name": "i"
        }
    ], 
    "constructors": [
        {
            "modifiers": [], 
            "name": "ActionPlansUtilities", 
            "parameters": [], 
            "visibility": "PUBLIC", 
            "references": [], 
            "location": {
                "column": 12, 
                "line": 55
            }, 
            "type": null
        }, 
        {
            "modifiers": [], 
            "name": "ActionPlansUtilities", 
            "parameters": [
                {
                    "type": "StandardController", 
                    "name": "stdController"
                }
            ], 
            "visibility": "PUBLIC", 
            "references": [], 
            "location": {
                "column": 12, 
                "line": 61
            }, 
            "type": null
        }, 
        {
            "modifiers": [], 
            "name": "ActionPlansUtilities", 
            "parameters": [
                {
                    "type": "ActionPlan__c", 
                    "name": "action"
                }
            ], 
            "visibility": "PUBLIC", 
            "references": [], 
            "location": {
                "column": 12, 
                "line": 67
            }, 
            "type": null
        }
    ], 
    "namespace": null, 
    "name": "ActionPlansUtilities", 
    "tableDeclaration": {
        "type": "ActionPlansUtilities", 
        "modifiers": [], 
        "references": [], 
        "location": {
            "column": 27, 
            "line": 35
        }, 
        "name": "ActionPlansUtilities"
    }, 
    "key": "01pF0000003RBxA", 
    "id": "01pF0000003RBxA", 
    "externalReferences": []
}